dash_snapshot_testing-1.2.2.dist-info/DESCRIPTION.rst
dash_snapshot_testing-1.2.2.dist-info/METADATA
dash_snapshot_testing-1.2.2.dist-info/RECORD
dash_snapshot_testing-1.2.2.dist-info/WHEEL
dash_snapshot_testing-1.2.2.dist-info/metadata.json
dash_snapshot_testing-1.2.2.dist-info/top_level.txt
snapshot_test/__init__.py
snapshot_test/snapshot_test_case.py
