Metadata-Version: 2.0
Name: dash-snapshot-testing
Version: 1.2.2
Summary: Dash snapshot testing package
Home-page: https://github.com/StratoDem/dash-snapshot-testing
Author: Michael Clawar, Eric Linden
Author-email: tech@stratodem.com
License: MIT
Keywords: dash snapshot plotly testing unittest
Platform: UNKNOWN
Requires-Python: >=3
Requires-Dist: dash (>=0.19.0)
Requires-Dist: plotly (>=2.2.3)
